{"modules":{"com.skypanther.tirotate.TiRotateModule":{"apiName":"TiRotate"}},"proxies":{"com.skypanther.tirotate.TiRotateModule":{"proxyClassName":"TiRotateModule","methods":{"setExifOrientation":{"hasInvocation":false,"defaultValueProvider":"org.appcelerator.kroll.KrollConverter","apiName":"setExifOrientation","runOnUiThread":false,"converter":"org.appcelerator.kroll.KrollConverter","args":[{"defaultValueProvider":"org.appcelerator.kroll.KrollConverter","converter":"org.appcelerator.kroll.KrollConverter","sourceName":"path","name":"path","type":"java.lang.String"},{"defaultValueProvider":"org.appcelerator.kroll.KrollConverter","converter":"org.appcelerator.kroll.KrollConverter","sourceName":"targetOrientation","name":"targetOrientation","type":"java.lang.Object"}],"name":"__default_name__","returnType":"void"},"rotate":{"hasInvocation":false,"defaultValueProvider":"org.appcelerator.kroll.KrollConverter","apiName":"rotate","runOnUiThread":false,"converter":"org.appcelerator.kroll.KrollConverter","args":[{"defaultValueProvider":"org.appcelerator.kroll.KrollConverter","converter":"org.appcelerator.kroll.KrollConverter","sourceName":"path","name":"path","type":"java.lang.String"},{"defaultValueProvider":"org.appcelerator.kroll.KrollConverter","converter":"org.appcelerator.kroll.KrollConverter","sourceName":"targetOrientation","name":"targetOrientation","type":"java.lang.String"}],"name":"__default_name__","returnType":"java.lang.Boolean"},"getExifOrientation":{"hasInvocation":false,"defaultValueProvider":"org.appcelerator.kroll.KrollConverter","apiName":"getExifOrientation","runOnUiThread":false,"converter":"org.appcelerator.kroll.KrollConverter","args":[{"defaultValueProvider":"org.appcelerator.kroll.KrollConverter","converter":"org.appcelerator.kroll.KrollConverter","sourceName":"path","name":"path","type":"java.lang.String"}],"name":"__default_name__","returnType":"java.lang.String"},"getExifOrientationDegrees":{"hasInvocation":false,"defaultValueProvider":"org.appcelerator.kroll.KrollConverter","apiName":"getExifOrientationDegrees","runOnUiThread":false,"converter":"org.appcelerator.kroll.KrollConverter","args":[{"defaultValueProvider":"org.appcelerator.kroll.KrollConverter","converter":"org.appcelerator.kroll.KrollConverter","sourceName":"path","name":"path","type":"java.lang.String"}],"name":"__default_name__","returnType":"int"}},"superProxyClassName":"KrollModule","superProxyBindingClassName":"org.appcelerator.kroll.KrollModuleBindingGen","proxyAttrs":{"proxyClassName":"com.skypanther.tirotate.TiRotateModule","id":"com.skypanther.tirotate","propertyAccessors":[],"isTopLevel":false,"name":"TiRotate","fullAPIName":"TiRotate"},"packageName":"com.skypanther.tirotate","sourceName":"com.skypanther.tirotate.TiRotateModuleBindingGen","superPackageName":"org.appcelerator.kroll","isModule":true,"genClassName":"TiRotateModuleBindingGen","constants":{"UPSIDE_PORTRAIT":{"name":"UPSIDE_PORTRAIT","value":"upside_portrait","proxyName":"UPSIDE_PORTRAIT","type":"java.lang.String"},"ORIENTATION_NORMAL":{"name":"ORIENTATION_NORMAL","value":1,"proxyName":"ORIENTATION_NORMAL","type":"int"},"PORTRAIT":{"name":"PORTRAIT","value":"portrait","proxyName":"PORTRAIT","type":"java.lang.String"},"ORIENTATION_ROTATE_90":{"name":"ORIENTATION_ROTATE_90","value":6,"proxyName":"ORIENTATION_ROTATE_90","type":"int"},"DEGREES_PORTRAIT":{"name":"DEGREES_PORTRAIT","value":0,"proxyName":"DEGREES_PORTRAIT","type":"int"},"ORIENTATION_ROTATE_270":{"name":"ORIENTATION_ROTATE_270","value":8,"proxyName":"ORIENTATION_ROTATE_270","type":"int"},"DEGREES_LANDSCAPE_LEFT":{"name":"DEGREES_LANDSCAPE_LEFT","value":270,"proxyName":"DEGREES_LANDSCAPE_LEFT","type":"int"},"LANDSCAPE_RIGHT":{"name":"LANDSCAPE_RIGHT","value":"landscape_right","proxyName":"LANDSCAPE_RIGHT","type":"java.lang.String"},"LANDSCAPE_LEFT":{"name":"LANDSCAPE_LEFT","value":"landscape_left","proxyName":"LANDSCAPE_LEFT","type":"java.lang.String"},"DEGREES_UPSIDE_PORTRAIT":{"name":"DEGREES_UPSIDE_PORTRAIT","value":180,"proxyName":"DEGREES_UPSIDE_PORTRAIT","type":"int"},"DEGREES_LANDSCAPE_RIGHT":{"name":"DEGREES_LANDSCAPE_RIGHT","value":90,"proxyName":"DEGREES_LANDSCAPE_RIGHT","type":"int"},"ORIENTATION_UNDEFINED":{"name":"ORIENTATION_UNDEFINED","value":0,"proxyName":"ORIENTATION_UNDEFINED","type":"int"},"ORIENTATION_ROTATE_180":{"name":"ORIENTATION_ROTATE_180","value":3,"proxyName":"ORIENTATION_ROTATE_180","type":"int"}},"onAppCreate":"onAppCreate"}}}